[
    {
        "title":"新手指南",
        "items":[
            {
                "title":"Minecraft 新手手册",
                "subtitle":"为不知道怎么游玩自己的 Minecraft 的玩家提供了一些建议，来解释你在游戏生存模式中的\n第一个白天应该做的事情，这样你就有更大的概率在游戏中的第一个夜晚存活下来了\n（Minecraft Wiki 中文）",
                "url":"https://minecraft.fandom.com/zh/wiki/%E6%95%99%E7%A8%8B/%E6%96%B0%E6%89%8B%E6%89%8B%E5%86%8C"
            },
            {
                "title":"新手问题",
                "subtitle":"这是一个提供给新手及小白的阅读文档",
                "url":"https://wifi-left.github.io/HMCL-docs-website/about-questions.html"
            },
            {
                "title":"HMCL 的自动安装使用教程",
                "subtitle":"他将告诉你如何用 HMCL 安装 Forge、Fabric、Fabric API、LiteLoader、Optifine \n以及 Mod 等",
                "url":"https://wifi-left.github.io/HMCL-docs-website/help/launcher/auto-installing.html"

            },
            {
                "title":"安装 Optifine / 光影",
                "subtitle":"他将告诉你如何安装 Optifine 来使用光影",
                "url":"https://wifi-left.github.io/HMCL-docs-website/install_optifine.html"
            }
        ]
    },
    {
        "title":"Minecraft",
        "items":[
            {
                "title":"存档损坏的解决方法",
                "subtitle":"游戏存档损坏，无法进入游戏的解决方法（Bilibili 视频）",
                "url":"https://www.bilibili.com/video/BV1yE41127He"
            },
            {
                "title":"导入存档",
                "subtitle":"他将告诉你如何导入 Minecraft 存档（地图）（Minecraft Wiki 中文）",
                "url":"https://minecraft.fandom.com/zh/wiki/%E6%95%99%E7%A8%8B/%E5%9C%B0%E5%9B%BE%E4%B8%8B%E8%BD%BD"
            },
            {
                "title":"安装资源包",
                "subtitle":"导入 Minecraft 资源包（纹理包）",
                "url":"https://minecraft.fandom.com/zh/wiki/%E6%95%99%E7%A8%8B/%E5%8A%A0%E8%BD%BD%E8%B5%84%E6%BA%90%E5%8C%85"
            },
            {
                "title":"安装整合包",
                "subtitle":"下载 / 导入 Minecraft 整合包"
            },
            {
                "title":"安装数据包",
                "subtitle":"在 HMCL 中导入 Minecraft 数据包（Minecraft Wiki 中文）",
                "url":"https://minecraft.fandom.com/zh/wiki/%E6%95%99%E7%A8%8B/%E5%AE%89%E8%A3%85%E6%95%B0%E6%8D%AE%E5%8C%85"
            }
        ]
    },
    {
        "title":"启动器",
        "items":[
            {
                "title":"排错指南",
                "subtitle":"他将告诉你游戏中一些简单报错的修复方法",
                "url":"https://wifi-left.github.io/HMCL-docs-website/debug.html"
            },
            {
                "title":"设置离线皮肤",
                "subtitle":"他将告诉你如何设置一个属于自己的离线皮肤",
                "url":"https://wifi-left.github.io/HMCL-docs-website/help/launcher/offline-skin.html"
            },
            {
                "title":"HMCL 多人联机帮助",
                "subtitle":"他将告诉你如何进行多人联机，以及一些常见问题解答",
                "url":"https://wifi-left.github.io/HMCL-docs-website/help/launcher/multiplayer.html"                
            },
            {
                "title":"版本隔离",
                "subtitle":"他可以帮助你更好的分离地图、模组等",
                "url":"https://wifi-left.github.io/HMCL-docs-website/help/launcher/isolation.html"
            },
            {
                "title":"设置游戏内存大小\n",
                "subtitle":"答：只需进入要调整内存大小的游戏版本的游戏管理或进入 设置-全局游戏设置 ,\n 在 游戏内存 中调整即可 "
            },
            {
                "title":"手动选择 Java",
                "subtitle":"答：只需进入要调整 Java 的游戏版本的游戏管理或进入 设置-全局游戏设置 ,\n 点击 Java 路径-自定义 并选择要使用的 Java 即可"
            },
            {
                "title":"添加 / 使用微软账户的一些问题解答",
                "subtitle":"在使用 / 添加微软账户时出现的一些问题的解答"
            },
            {
                "title":"设置 / 添加外置登陆账户（authlib-injector）",
                "subtitle":"添加外置登录登陆认证服务器和添加外置登陆账户帮助"
            },
            {
                "title": "Authlib-Injector 服务器设置指南",
                "subtitle": "手动打包整合包后，启动游戏时直接弹出对应的账号登录页",
                "url": "https://hmcl.huangyuhui.net/help/launcher/authlib-injector.html"
            },
            {
                "title": "数据包制作指南",
                "subtitle": "制作可以由 HMCL 导入的数据包",
                "url": "https://hmcl.huangyuhui.net/help/launcher/datapack.html"
            },
            {
                "title": "服务端自动更新整合包制作教程",
                "subtitle": "服务端自动更新整合包允许启动器根据服主配置强制更新玩家游戏客户端",
                "url": "https://wifi-left.github.io/HMCL-docs-website/help/launcher/serverpack.html"
            },
            {
                "title":"整合包自带 Java",
                "subtitle":"他将告诉你如何在整合包中包含 Java",
                "url":"https://wifi-left.github.io/HMCL-docs-website/modpack-in-java.html"
            }
        ]
    },
    {
        "title":"HMCL 整合包",
        "items":[
            {
                "title": "Authlib-Injector 服务器设置指南",
                "subtitle": "手动打包整合包后，启动游戏时直接弹出对应的账号登录页",
                "url": "https://hmcl.huangyuhui.net/help/launcher/authlib-injector.html"
            },
            {
                "title": "服务端自动更新整合包制作教程",
                "subtitle": "服务端自动更新整合包允许启动器根据服主配置强制更新玩家游戏客户端",
                "url": "https://wifi-left.github.io/HMCL-docs-website/help/launcher/serverpack.html"
            },
            {
                "title":"整合包自带 Java",
                "subtitle":"他将告诉你如何在整合包中包含 Java",
                "url":"https://wifi-left.github.io/HMCL-docs-website/modpack-in-java.html"
            }
        ]
    },
    {
        "title":"关于",
        "items":[
            {
                "title":"更多文章访问",
                "subtitle":"文章最终来源：https://wifi-left.github.io/HMCL-docs-website",
                "url":"https://wifi-left.github.io/HMCL-docs-website/index-help.html"
            },
            {
                "title":"为 HMCL 帮助文档出一份力",
                "subtitle":"为 HMCL 帮助文档出一份力吧，让更多人看到 HMCL 帮助文档",
                "url":"https://wifi-left.github.io/HMCL-docs-website/help/contribution.html"
            }
        ]
    }
]
